{
  "REALTIME": {
    "tableName": "ingest_kafka_REALTIME",
    "tableType": "REALTIME",
    "segmentsConfig": {
      "replicasPerPartition": "1",
      "timeType": "MILLISECONDS",
      "timeColumnName": "timestamp",
      "minimizeDataMovement": false
    },
    "tenants": {
      "broker": "DefaultTenant",
      "server": "DefaultTenant"
    },
    "tableIndexConfig": {
      "rangeIndexVersion": 2,
      "autoGeneratedInvertedIndex": false,
      "createInvertedIndexDuringSegmentGeneration": false,
      "loadMode": "MMAP",
      "enableDefaultStarTree": false,
      "enableDynamicStarTreeCreation": false,
      "aggregateMetrics": false,
      "nullHandlingEnabled": false,
      "columnMajorSegmentBuilderEnabled": true,
      "skipSegmentPreprocess": false,
      "optimizeNoDictStatsCollection": false,
      "optimizeDictionary": false,
      "optimizeDictionaryForMetrics": false,
      "optimizeDictionaryType": false,
      "noDictionarySizeRatioThreshold": 0.85,
      "streamConfigs": {
        "streamType": "kafka",
        "stream.kafka.topic.name": "ingest-kafka",
        "stream.kafka.decoder.class.name": "org.apache.pinot.plugin.inputformat.json.JSONMessageDecoder",
        "stream.kafka.consumer.factory.class.name": "org.apache.pinot.plugin.stream.kafka20.KafkaConsumerFactory",
        "stream.kafka.broker.list": "kafka:9092",
        "realtime.segment.flush.threshold.rows": "0",
        "realtime.segment.flush.threshold.time": "24h",
        "realtime.segment.flush.threshold.segment.size": "50M",
        "stream.kafka.consumer.prop.auto.offset.reset": "smallest"
      }
    },
    "metadata": {
      "customConfigs": {}
    },
    "fieldConfigList": [
      {
        "name": "content",
        "encodingType": "RAW",
        "indexType": "TEXT",
        "indexTypes": [
          "TEXT"
        ],
        "indexes": null,
        "tierOverwrites": null
      }
    ],
    "isDimTable": false
  }
}